i_xero/__init__.py
i_xero/i_flask.py
i_xero/i_xero.py
i_xero/i_xero2.py
i_xero-1.0.0a3.dist-info/LICENSE
i_xero-1.0.0a3.dist-info/WHEEL
i_xero-1.0.0a3.dist-info/METADATA
i_xero-1.0.0a3.dist-info/RECORD
