Metadata-Version: 2.1
Name: i_xero
Version: 1.0.0a3
Summary: A set of functions to retrieve and save data into Xero.
Home-page: https://github.com/aracnid/i-xero
Keywords: i-xero,xero
Author: Jason Romano
Author-email: aracnid@gmail.com
Requires-Python: ~=3.9
Classifier: License :: Other/Proprietary License
Requires-Dist: aracnid-logger
Requires-Dist: flask
Requires-Dist: flask-oauthlib
Requires-Dist: flask-session
Requires-Dist: i-mongodb
Requires-Dist: pytz
Requires-Dist: pyxero
Requires-Dist: xero-python
